nostpy/Event.py
nostpy/Kind4.py
nostpy/Query.py
nostpy/Subscription.py
nostpy/Websocket.py
nostpy/__init__.py
nostpy-0.1.0.dist-info/LICENSE
nostpy-0.1.0.dist-info/METADATA
nostpy-0.1.0.dist-info/WHEEL
nostpy-0.1.0.dist-info/entry_points.txt
nostpy-0.1.0.dist-info/top_level.txt
nostpy-0.1.0.dist-info/RECORD
